LICENSE
MANIFEST.in
README
openerp-server
setup.cfg
setup.py
doc/01_getting_started.rst
doc/02_architecture.rst
doc/03_module_dev.rst
doc/03_module_dev_01.rst
doc/03_module_dev_02.rst
doc/03_module_dev_03.rst
doc/03_module_dev_04.rst
doc/03_module_dev_05.rst
doc/03_module_dev_06.rst
doc/04_security.rst
doc/05_test_framework.rst
doc/06_misc.rst
doc/06_misc_auto_join.rst
doc/06_misc_import.rst
doc/06_misc_import_o2m.txt
doc/06_misc_list_font_style.rst
doc/06_misc_need_action_specs.rst
doc/06_misc_on_change_tips.rst
doc/06_misc_user_img_specs.rst
doc/09_deployment.rst
doc/Makefile
doc/api_models.rst
doc/changelog.rst
doc/conf.py
doc/index.rst
doc/_static/02_mvc_diagram.png
doc/_static/02_openerp_architecture.png
doc/_static/03_module_gen_view.png
doc/_static/openerp.png
doc/_templates/sidebarintro.html
doc/_templates/sidebarlogo.html
doc/_themes/.gitignore
doc/_themes/LICENSE
doc/_themes/README
doc/_themes/flask_theme_support.py
doc/_themes/flask/layout.html
doc/_themes/flask/relations.html
doc/_themes/flask/theme.conf
doc/_themes/flask/static/flasky.css_t
doc/_themes/flask/static/small_flask.css
doc/_themes/flask_small/layout.html
doc/_themes/flask_small/theme.conf
doc/_themes/flask_small/static/flasky.css_t
openerp/__init__.py
openerp/exceptions.py
openerp/import_xml.rng
openerp/loglevels.py
openerp/netsvc.py
openerp/pooler.py
openerp/release.py
openerp/sql_db.py
openerp/addons/__init__.py
openerp/addons/base_quality_interrogation.py
openerp/addons/base/__init__.py
openerp/addons/base/__openerp__.py
openerp/addons/base/base.sql
openerp/addons/base/base_data.xml
openerp/addons/base/base_demo.xml
openerp/addons/base/base_menu.xml
openerp/addons/base/currency_data.xml
openerp/addons/base/data/administration-hover.png
openerp/addons/base/data/administration.png
openerp/addons/base/data/res.country.state.csv
openerp/addons/base/data/sales-hover.png
openerp/addons/base/data/sales.png
openerp/addons/base/i18n/ab.po
openerp/addons/base/i18n/af.po
openerp_core.egg-info/PKG-INFO
openerp_core.egg-info/SOURCES.txt
openerp_core.egg-info/dependency_links.txt
openerp_core.egg-info/requires.txt
openerp_core.egg-info/top_level.txt